opentelemetry_python/__init__.py
opentelemetry_python/aiokafka.py
opentelemetry_python/fastapi.py
opentelemetry_python/grpc.py
opentelemetry_python/kafka.py
opentelemetry_python/tracer.py
opentelemetry_python-0.4.dist-info/METADATA
opentelemetry_python-0.4.dist-info/WHEEL
opentelemetry_python-0.4.dist-info/top_level.txt
opentelemetry_python-0.4.dist-info/RECORD
